<annotation>
	<folder>train</folder>
	<filename>DARK SOULS 02_05_2018 18_52_21.png</filename>
	<path>C:\PFG\Imagenes\images_03_05_2018\train\DARK SOULS 02_05_2018 18_52_21.png</path>
	<source>
		<database>Unknown</database>
	</source>
	<size>
		<width>1024</width>
		<height>576</height>
		<depth>3</depth>
	</size>
	<segmented>0</segmented>
	<object>
		<name>bonfire</name>
		<pose>Unspecified</pose>
		<truncated>0</truncated>
		<difficult>0</difficult>
		<bndbox>
			<xmin>467</xmin>
			<ymin>326</ymin>
			<xmax>528</xmax>
			<ymax>442</ymax>
		</bndbox>
	</object>
	<object>
		<name>player</name>
		<pose>Unspecified</pose>
		<truncated>0</truncated>
		<difficult>0</difficult>
		<bndbox>
			<xmin>251</xmin>
			<ymin>274</ymin>
			<xmax>432</xmax>
			<ymax>565</ymax>
		</bndbox>
	</object>
</annotation>
